bot/__init__.py
bot/core.py
bot/handlers.py
bot/settings.py
bot/util_decorators.py
bot/util_functions.py
bot/util_ping.py
examples/__init__.py
examples/__main__.py
examples/echo_bot.py
examples/host_watch_bot.py
examples/http_server.py
examples/remove_pypi.py
examples/util_watch.py
examples/hostwatch/__init__.py
tlgbotfwk-0.4.61.dist-info/LICENSE
tlgbotfwk-0.4.61.dist-info/METADATA
tlgbotfwk-0.4.61.dist-info/WHEEL
tlgbotfwk-0.4.61.dist-info/top_level.txt
tlgbotfwk-0.4.61.dist-info/RECORD
